siteblocks/__init__.py
siteblocks/admin.py
siteblocks/apps.py
siteblocks/models.py
siteblocks/settings.py
siteblocks/siteblocksapp.py
siteblocks/locale/en/LC_MESSAGES/django.po
siteblocks/locale/fr/LC_MESSAGES/django.mo
siteblocks/locale/fr/LC_MESSAGES/django.po
siteblocks/locale/ru/LC_MESSAGES/django.mo
siteblocks/locale/ru/LC_MESSAGES/django.po
siteblocks/migrations/0001_initial.py
siteblocks/migrations/0002_auto_20140921_1038.py
siteblocks/migrations/0003_auto_20140925_1046.py
siteblocks/migrations/__init__.py
siteblocks/templatetags/__init__.py
siteblocks/templatetags/siteblocks.py
siteblocks/tests/__init__.py
siteblocks/tests/conftest.py
siteblocks/tests/test_basic.py
siteblocks/tests/testapp/__init__.py
siteblocks/tests/testapp/urls.py
django_siteblocks-1.2.1.dist-info/AUTHORS
django_siteblocks-1.2.1.dist-info/LICENSE
django_siteblocks-1.2.1.dist-info/METADATA
django_siteblocks-1.2.1.dist-info/WHEEL
django_siteblocks-1.2.1.dist-info/top_level.txt
django_siteblocks-1.2.1.dist-info/RECORD
